{
  "manifestVersion": "3.2",
  "admin": {
    "address": "0xc16893488bC372663E1923D456Fd3a0e40B4891F",
    "txHash": "0x1c0b991cab19982bf8ce5a54e3b52cf262345c98506fdd6b2c6cf82b594cd490"
  },
  "proxies": [
    {
      "address": "0x60b4c70A96D21978a9bf98B57179A726d77F743F",
      "txHash": "0x8d17f8f67d917182414e54f9df5d36d6315c5ef1ff13ba5133b495c0b6a8573c",
      "kind": "transparent"
    },
    {
      "address": "0x5d2E8D7306e6e5C480715DA9369901e2c27b51f8",
      "txHash": "0xd4fa40ffe1436f8aa12ef875a0215fc306e45a38b7e9fdea7d2f37390ffe7688",
      "kind": "transparent"
    }
  ],
  "impls": {
    "f15c9d3f78ea06598a841337eed11edd2d8932c6955d9c3874839fec476ad570": {
      "address": "0xd30F87a3d99d78850d99402B456541964Bdac49a",
      "txHash": "0x6d81f99071e167f1b5b6f635088bcdcebad542a465f679ec2ed7202e149e47f1",
      "layout": {
        "storage": [
          {
            "label": "_initialized",
            "offset": 0,
            "slot": "0",
            "type": "t_uint8",
            "contract": "Initializable",
            "src": "@openzeppelin/contracts-upgradeable/proxy/utils/Initializable.sol:62",
            "retypedFrom": "bool"
          },
          {
            "label": "_initializing",
            "offset": 1,
            "slot": "0",
            "type": "t_bool",
            "contract": "Initializable",
            "src": "@openzeppelin/contracts-upgradeable/proxy/utils/Initializable.sol:67"
          },
          {
            "label": "owner",
            "offset": 2,
            "slot": "0",
            "type": "t_address",
            "contract": "Auth",
            "src": "contracts/libs/app/Auth.sol:9"
          },
          {
            "label": "__gap",
            "offset": 0,
            "slot": "1",
            "type": "t_array(t_uint256)50_storage",
            "contract": "ContextUpgradeable",
            "src": "@openzeppelin/contracts-upgradeable/utils/ContextUpgradeable.sol:36"
          },
          {
            "label": "mintAble",
            "offset": 0,
            "slot": "51",
            "type": "t_mapping(t_address,t_bool)",
            "contract": "NFTAuth",
            "src": "contracts/libs/app/NFTAuth.sol:9"
          },
          {
            "label": "transferable",
            "offset": 0,
            "slot": "52",
            "type": "t_mapping(t_address,t_bool)",
            "contract": "NFTAuth",
            "src": "contracts/libs/app/NFTAuth.sol:10"
          },
          {
            "label": "waitingList",
            "offset": 0,
            "slot": "53",
            "type": "t_mapping(t_address,t_bool)",
            "contract": "NFTAuth",
            "src": "contracts/libs/app/NFTAuth.sol:11"
          },
          {
            "label": "__gap",
            "offset": 0,
            "slot": "54",
            "type": "t_array(t_uint256)50_storage",
            "contract": "ERC165Upgradeable",
            "src": "@openzeppelin/contracts-upgradeable/utils/introspection/ERC165Upgradeable.sol:41"
          },
          {
            "label": "_name",
            "offset": 0,
            "slot": "104",
            "type": "t_string_storage",
            "contract": "ERC721Upgradeable",
            "src": "@openzeppelin/contracts-upgradeable/token/ERC721/ERC721Upgradeable.sol:25"
          },
          {
            "label": "_symbol",
            "offset": 0,
            "slot": "105",
            "type": "t_string_storage",
            "contract": "ERC721Upgradeable",
            "src": "@openzeppelin/contracts-upgradeable/token/ERC721/ERC721Upgradeable.sol:28"
          },
          {
            "label": "_owners",
            "offset": 0,
            "slot": "106",
            "type": "t_mapping(t_uint256,t_address)",
            "contract": "ERC721Upgradeable",
            "src": "@openzeppelin/contracts-upgradeable/token/ERC721/ERC721Upgradeable.sol:31"
          },
          {
            "label": "_balances",
            "offset": 0,
            "slot": "107",
            "type": "t_mapping(t_address,t_uint256)",
            "contract": "ERC721Upgradeable",
            "src": "@openzeppelin/contracts-upgradeable/token/ERC721/ERC721Upgradeable.sol:34"
          },
          {
            "label": "_tokenApprovals",
            "offset": 0,
            "slot": "108",
            "type": "t_mapping(t_uint256,t_address)",
            "contract": "ERC721Upgradeable",
            "src": "@openzeppelin/contracts-upgradeable/token/ERC721/ERC721Upgradeable.sol:37"
          },
          {
            "label": "_operatorApprovals",
            "offset": 0,
            "slot": "109",
            "type": "t_mapping(t_address,t_mapping(t_address,t_bool))",
            "contract": "ERC721Upgradeable",
            "src": "@openzeppelin/contracts-upgradeable/token/ERC721/ERC721Upgradeable.sol:40"
          },
          {
            "label": "__gap",
            "offset": 0,
            "slot": "110",
            "type": "t_array(t_uint256)44_storage",
            "contract": "ERC721Upgradeable",
            "src": "@openzeppelin/contracts-upgradeable/token/ERC721/ERC721Upgradeable.sol:465"
          },
          {
            "label": "totalSupply",
            "offset": 0,
            "slot": "154",
            "type": "t_uint256",
            "contract": "JobNFT",
            "src": "contracts/JobNFT.sol:11"
          },
          {
            "label": "tokenCounter",
            "offset": 0,
            "slot": "155",
            "type": "t_uint256",
            "contract": "JobNFT",
            "src": "contracts/JobNFT.sol:12"
          }
        ],
        "types": {
          "t_address": {
            "label": "address",
            "numberOfBytes": "20"
          },
          "t_array(t_uint256)44_storage": {
            "label": "uint256[44]",
            "numberOfBytes": "1408"
          },
          "t_array(t_uint256)50_storage": {
            "label": "uint256[50]",
            "numberOfBytes": "1600"
          },
          "t_bool": {
            "label": "bool",
            "numberOfBytes": "1"
          },
          "t_mapping(t_address,t_bool)": {
            "label": "mapping(address => bool)",
            "numberOfBytes": "32"
          },
          "t_mapping(t_address,t_mapping(t_address,t_bool))": {
            "label": "mapping(address => mapping(address => bool))",
            "numberOfBytes": "32"
          },
          "t_mapping(t_address,t_uint256)": {
            "label": "mapping(address => uint256)",
            "numberOfBytes": "32"
          },
          "t_mapping(t_uint256,t_address)": {
            "label": "mapping(uint256 => address)",
            "numberOfBytes": "32"
          },
          "t_string_storage": {
            "label": "string",
            "numberOfBytes": "32"
          },
          "t_uint256": {
            "label": "uint256",
            "numberOfBytes": "32"
          },
          "t_uint8": {
            "label": "uint8",
            "numberOfBytes": "1"
          }
        }
      }
    },
    "c3e9fe2524ea0658bc0d91ab84509cbbd94854a7dd2468e15504b504bfa31bf1": {
      "address": "0x976AA769DbB5f2F25CC9bfb966823F33A5215cCC",
      "txHash": "0x0912cebd0b706dd40d3f7e2cbf9cc58293a80eb4651044aaacfcfd71b20122ff",
      "layout": {
        "storage": [
          {
            "label": "_initialized",
            "offset": 0,
            "slot": "0",
            "type": "t_uint8",
            "contract": "Initializable",
            "src": "@openzeppelin/contracts-upgradeable/proxy/utils/Initializable.sol:62",
            "retypedFrom": "bool"
          },
          {
            "label": "_initializing",
            "offset": 1,
            "slot": "0",
            "type": "t_bool",
            "contract": "Initializable",
            "src": "@openzeppelin/contracts-upgradeable/proxy/utils/Initializable.sol:67"
          },
          {
            "label": "owner",
            "offset": 2,
            "slot": "0",
            "type": "t_address",
            "contract": "Auth",
            "src": "contracts/libs/app/Auth.sol:9"
          },
          {
            "label": "_HASHED_NAME",
            "offset": 0,
            "slot": "1",
            "type": "t_bytes32",
            "contract": "EIP712Upgradeable",
            "src": "@openzeppelin/contracts-upgradeable/utils/cryptography/draft-EIP712Upgradeable.sol:32"
          },
          {
            "label": "_HASHED_VERSION",
            "offset": 0,
            "slot": "2",
            "type": "t_bytes32",
            "contract": "EIP712Upgradeable",
            "src": "@openzeppelin/contracts-upgradeable/utils/cryptography/draft-EIP712Upgradeable.sol:33"
          },
          {
            "label": "__gap",
            "offset": 0,
            "slot": "3",
            "type": "t_array(t_uint256)50_storage",
            "contract": "EIP712Upgradeable",
            "src": "@openzeppelin/contracts-upgradeable/utils/cryptography/draft-EIP712Upgradeable.sol:120"
          },
          {
            "label": "usdtToken",
            "offset": 0,
            "slot": "53",
            "type": "t_contract(IBEP20)2511",
            "contract": "UCReferral",
            "src": "contracts/UCReferral.sol:12"
          },
          {
            "label": "config",
            "offset": 0,
            "slot": "54",
            "type": "t_struct(Config)1342_storage",
            "contract": "UCReferral",
            "src": "contracts/UCReferral.sol:52"
          },
          {
            "label": "jobNFT",
            "offset": 0,
            "slot": "61",
            "type": "t_contract(IJobNFT)2376",
            "contract": "UCReferral",
            "src": "contracts/UCReferral.sol:53"
          },
          {
            "label": "jobs",
            "offset": 0,
            "slot": "62",
            "type": "t_mapping(t_bytes32,t_struct(Job)1367_storage)",
            "contract": "UCReferral",
            "src": "contracts/UCReferral.sol:54"
          },
          {
            "label": "nonce",
            "offset": 0,
            "slot": "63",
            "type": "t_mapping(t_address,t_uint256)",
            "contract": "UCReferral",
            "src": "contracts/UCReferral.sol:55"
          }
        ],
        "types": {
          "t_address": {
            "label": "address",
            "numberOfBytes": "20"
          },
          "t_array(t_uint256)50_storage": {
            "label": "uint256[50]",
            "numberOfBytes": "1600"
          },
          "t_bool": {
            "label": "bool",
            "numberOfBytes": "1"
          },
          "t_bytes32": {
            "label": "bytes32",
            "numberOfBytes": "32"
          },
          "t_contract(IBEP20)2511": {
            "label": "contract IBEP20",
            "numberOfBytes": "20"
          },
          "t_contract(IJobNFT)2376": {
            "label": "contract IJobNFT",
            "numberOfBytes": "20"
          },
          "t_enum(Result)1327": {
            "label": "enum UCReferral.Result",
            "members": [
              "PENDING",
              "SUCCESS",
              "FAIL"
            ],
            "numberOfBytes": "1"
          },
          "t_enum(Status)1323": {
            "label": "enum UCReferral.Status",
            "members": [
              "CREATED",
              "DISPUTED",
              "CLOSED",
              "COMPLETED"
            ],
            "numberOfBytes": "1"
          },
          "t_mapping(t_address,t_uint256)": {
            "label": "mapping(address => uint256)",
            "numberOfBytes": "32"
          },
          "t_mapping(t_bytes32,t_struct(Job)1367_storage)": {
            "label": "mapping(bytes32 => struct UCReferral.Job)",
            "numberOfBytes": "32"
          },
          "t_struct(Config)1342_storage": {
            "label": "struct UCReferral.Config",
            "members": [
              {
                "label": "ecosystemFeePercentage",
                "type": "t_uint256",
                "offset": 0,
                "slot": "0"
              },
              {
                "label": "referralFeePercentage",
                "type": "t_uint256",
                "offset": 0,
                "slot": "1"
              },
              {
                "label": "disputeFeePercentage",
                "type": "t_uint256",
                "offset": 0,
                "slot": "2"
              },
              {
                "label": "baseReferalPercentage",
                "type": "t_uint256",
                "offset": 0,
                "slot": "3"
              },
              {
                "label": "freezePeriod",
                "type": "t_uint256",
                "offset": 0,
                "slot": "4"
              },
              {
                "label": "treasury",
                "type": "t_address",
                "offset": 0,
                "slot": "5"
              },
              {
                "label": "serverSigner",
                "type": "t_address",
                "offset": 0,
                "slot": "6"
              }
            ],
            "numberOfBytes": "224"
          },
          "t_struct(Job)1367_storage": {
            "label": "struct UCReferral.Job",
            "members": [
              {
                "label": "creator",
                "type": "t_address",
                "offset": 0,
                "slot": "0"
              },
              {
                "label": "talent",
                "type": "t_address",
                "offset": 0,
                "slot": "1"
              },
              {
                "label": "referrer",
                "type": "t_address",
                "offset": 0,
                "slot": "2"
              },
              {
                "label": "referalPercentage",
                "type": "t_uint256",
                "offset": 0,
                "slot": "3"
              },
              {
                "label": "amount",
                "type": "t_uint256",
                "offset": 0,
                "slot": "4"
              },
              {
                "label": "timestamp",
                "type": "t_uint256",
                "offset": 0,
                "slot": "5"
              },
              {
                "label": "closeTimestamp",
                "type": "t_uint256",
                "offset": 0,
                "slot": "6"
              },
              {
                "label": "disputeTimestamp",
                "type": "t_uint256",
                "offset": 0,
                "slot": "7"
              },
              {
                "label": "nftId",
                "type": "t_uint256",
                "offset": 0,
                "slot": "8"
              },
              {
                "label": "status",
                "type": "t_enum(Status)1323",
                "offset": 0,
                "slot": "9"
              },
              {
                "label": "result",
                "type": "t_enum(Result)1327",
                "offset": 1,
                "slot": "9"
              }
            ],
            "numberOfBytes": "320"
          },
          "t_uint256": {
            "label": "uint256",
            "numberOfBytes": "32"
          },
          "t_uint8": {
            "label": "uint8",
            "numberOfBytes": "1"
          }
        }
      }
    }
  }
}
